epyt_c/__init__.py
epyt_c/arsenite_oxidation_arsenate_attachment_detachment.py
epyt_c/bacterial_regrowth.py
epyt_c/chlorine_decay_thms_formation.py
epyt_c/default_values.yaml
epyt_c/functions.py
epyt_c/main.py
epyt_c/pfas_formation.py
epyt_c/run.py
epyt_c-0.1.0.dist-info/AUTHORS.rst
epyt_c-0.1.0.dist-info/LICENSE
epyt_c-0.1.0.dist-info/METADATA
epyt_c-0.1.0.dist-info/WHEEL
epyt_c-0.1.0.dist-info/top_level.txt
epyt_c-0.1.0.dist-info/RECORD
