Metadata-Version: 2.1
Name: epyt_c
Version: 0.1.0
Summary: An open-source Python package for modeling water quality in water distribution systems
Home-page: https://github.com/SWIL-IITK/EPyT-C
Author: Gopinbathan R Abhijith
Author-email: abhijith@iitk.ac.in
Keywords: epanet,water,networks,quality,simulations,water quality modelling
Classifier: Programming Language :: Python :: 3.8
Classifier: Programming Language :: Python :: 3.9
Classifier: Programming Language :: Python :: 3.10
Classifier: Programming Language :: Python :: 3.11
Classifier: Programming Language :: Python :: 3.12
Classifier: Programming Language :: Python
Classifier: Operating System :: OS Independent
Requires-Python: >=3.8
License-File: LICENSE
License-File: AUTHORS.rst
Requires-Dist: epyt
